fastapi_commons/__init__.py
fastapi_commons/auth.py
fastapi_commons/conf.py
fastapi_commons/handlers.py
fastapi_commons/instrumentation.py
fastapi_commons/middleware.py
fastapi_commons/permissions.py
fastapi_commons/db/__init__.py
fastapi_commons/db/helpers.py
fastapi_commons/db/models/__init__.py
fastapi_commons/db/models/auth.py
fastapi_commons/db/models/rbac.py
fastapi_commons-0.2.25.dist-info/licenses/AUTHORS.rst
fastapi_commons-0.2.25.dist-info/licenses/LICENSE
fastapi_commons-0.2.25.dist-info/METADATA
fastapi_commons-0.2.25.dist-info/WHEEL
fastapi_commons-0.2.25.dist-info/top_level.txt
fastapi_commons-0.2.25.dist-info/RECORD
